[
    {
        "name": "Gin",
        "drinkID": 1,
        "position": null
    },
    {
        "name": "Vodka", 
        "drinkID": 2,
        "position": null
    },
    {
        "name": "Aperol", 
        "drinkID": 3,
        "position": null
    },
    {
        "name": "Martini",
        "drinkID": 4,
        "position": null
    },
    {
        "name": "Lime Juice",
        "drinkID": 5,
        "position": null
    },
    {
        "name": "Orangen-Saft",
        "drinkID": 6,
        "position": null
    },
    {
        "name":"Ananas-Saft",   
        "drinkID": 7,
        "position": null
    },
    {
        "name": "Zitronen-Saft",
        "drinkID": 8,
        "position": null
    },
    {
        "name": "Soda",
        "drinkID": 9,
        "position": null
    }
]